docx_parsing_gmdzy2010/__init__.py
docx_parsing_gmdzy2010/elements.py
docx_parsing_gmdzy2010/renderer.py
docx_parsing_gmdzy2010/settings.py
docx_parsing_gmdzy2010/utilities.py
docx_parsing_gmdzy2010-1.3.1.dist-info/DESCRIPTION.rst
docx_parsing_gmdzy2010-1.3.1.dist-info/METADATA
docx_parsing_gmdzy2010-1.3.1.dist-info/RECORD
docx_parsing_gmdzy2010-1.3.1.dist-info/WHEEL
docx_parsing_gmdzy2010-1.3.1.dist-info/metadata.json
docx_parsing_gmdzy2010-1.3.1.dist-info/top_level.txt
