Metadata-Version: 2.0
Name: docx-parsing-gmdzy2010
Version: 1.3.1
Summary: 一个简单的文本模板转DOCX文件的包
Home-page: https://github.com/gmdzy2010/docx_parsing_gmdzy2010
Author: gmdzy2010
Author-email: gmdzy2010@126.com
License: MIT License
Keywords: docx;text;template
Platform: UNKNOWN
Classifier: Programming Language :: Python :: 3
Classifier: Programming Language :: Python :: 3.4
Classifier: Programming Language :: Python :: 3.5
Classifier: Programming Language :: Python :: 3.6
Classifier: License :: OSI Approved :: MIT License
Classifier: Operating System :: OS Independent
